ensemble_tabpfn/__init__.py
ensemble_tabpfn/ensemble_tabpfn.py
ensemble_tabpfn/samplers/__init__.py
ensemble_tabpfn/samplers/data.py
ensemble_tabpfn/samplers/features.py
ensemble_tabpfn/utils.py
ensemble_tabpfn-0.1.1.dist-info/LICENSE
ensemble_tabpfn-0.1.1.dist-info/METADATA
ensemble_tabpfn-0.1.1.dist-info/WHEEL
ensemble_tabpfn-0.1.1.dist-info/RECORD
