Metadata-Version: 2.1
Name: ensemble-tabpfn
Version: 0.1.1
Summary: Adaptation of TabPFN to work with large tabular datasets.
Home-page: https://github.com/ersilia-os/ensemble-tabpfn
License: GPL-3.0-only
Author: Ersilia Open Source Initiative
Requires-Python: >=3.8.1,<4.0.0
Classifier: License :: OSI Approved :: GNU General Public License v3 (GPLv3)
Classifier: Programming Language :: Python :: 3
Classifier: Programming Language :: Python :: 3.9
Classifier: Programming Language :: Python :: 3.10
Classifier: Programming Language :: Python :: 3.11
Requires-Dist: lolP (==0.0.4)
Requires-Dist: tabpfn (==0.1.8)
Project-URL: Repository, https://github.com/ersilia-os/ensemble-tabpfn
